CONTRIBUTORS.rst
MANIFEST.in
README.rst
setup.py
bin/stupid-script
melbdjango_joke.egg-info/PKG-INFO
melbdjango_joke.egg-info/SOURCES.txt
melbdjango_joke.egg-info/dependency_links.txt
melbdjango_joke.egg-info/entry_points.txt
melbdjango_joke.egg-info/not-zip-safe
melbdjango_joke.egg-info/requires.txt
melbdjango_joke.egg-info/top_level.txt
thejoke/__init__.py
thejoke/teller.py