Metadata-Version: 1.1
Name: melbdjango-joke
Version: 0.3
Summary: Lulz
Home-page: http://github.com/GVRV/melbdjango-demo/
Author: Gaurav Dadhania
Author-email: gaurav@dadhania.in
License: MIT
Keywords: melbdjango joke
Platform: UNKNOWN
Classifier: Development Status :: 1 - Planning
Classifier: Intended Audience :: Developers
Classifier: License :: OSI Approved :: MIT License
